Workbook

Sheet Dashboard
C16: KPI | D16: Formula | E16: Example Output
C17: Total Transactions | D17: =COUNTA(Reconciliation!A1) | E17: 1
C18: Matches | D18: =COUNTIF(Reconciliation!F:F,"Match") | E18: 16
C19: Mismatches | D19: =COUNTIF(Reconciliation!F:F,"Mismatch") | E19: 34
C20: Data Accuracy % | D20: =COUNTIF(Reconciliation!F:F,"Match")/COUNTA(Reconciliation!A:A) | E20: 0.31372549

Sheet Exception Summary
A1: Match Status | B1: Mismatch
A3: Corporate_Action_Type | B3: Count of Match Status
A4: Bonus Issue | B4: 8
A5: Buyback | B5: 8
A6: Dividend | B6: 9
A7: Merger | B7: 6
A8: Split | B8: 3
A9: Grand Total | B9: 34

Sheet Asset_Servicing_Reconciliation
B3: Match Status | C3: Count of System A Transaction ID)
B4: Match | C4: 16
B5: Mismatch | C5: 34
B6: (blank)
B7: Grand Total | C7: 50

Sheet UAT_Tracker
A1: Test Case ID | B1: Scenario | C1: Expected Result | D1: Actual Result | E1: Status | F1: Tester Comments
A2: TC001 | B2: Validate XLOOKUP for Reconciliation | C2: Matching transactions display “Match” | D2: “Match” appears correctly | E2: Pass | F2: Working
A3: TC002 | B3: Identify mismatched quantities | C3: Mismatch flag for incorrect quantities | D3: Mismatch flagged correctly | E3: Pass | F3: Working
A4: TC003 | B4: Handle missing IDs | C4: “Not Found” message displayed | D4: Error shown | E4: Fail | F4: Needs review
A5: TC004 | B5: Validate PivotTable data | C5: Validate PivotTable data | D5: Pivot count matches raw data | E5: In Progress | F5: Rechecking filter setup

Sheet Reconciliation
A1: System A Transaction ID) | B1: Security_Type | C1: Corporate_Action_Type | D1: Quantity in System A | E1: Quantity in System B | F1: Match Status
A2: TXN1001 | B2: Equity | C2: Buyback | D2: 481 | E2: =_xlfn.XLOOKUP(A2,System_B!A:A,System_B!D:D) -> 481 | F2: Match
A3: TXN1002 | B3: Equity | C3: Buyback | D3: 443 | E3: =_xlfn.XLOOKUP(A3,System_B!A:A,System_B!D:D) -> 448 | F3: Mismatch
A4: TXN1003 | B4: ETF | C4: Merger | D4: 447 | E4: =_xlfn.XLOOKUP(A4,System_B!A:A,System_B!D:D) -> 447 | F4: Match
A5: TXN1004 | B5: Bond | C5: Bonus Issue | D5: 78 | E5: =_xlfn.XLOOKUP(A5,System_B!A:A,System_B!D:D) -> 78 | F5: Match
A6: TXN1005 | B6: Bond | C6: Buyback | D6: 167 | E6: =_xlfn.XLOOKUP(A6,System_B!A:A,System_B!D:D) -> 162 | F6: Mismatch
A7: TXN1006 | B7: Bond | C7: Bonus Issue | D7: 470 | E7: =_xlfn.XLOOKUP(A7,System_B!A:A,System_B!D:D) -> 465 | F7: Mismatch
A8: TXN1007 | B8: Equity | C8: Split | D8: 66 | E8: =_xlfn.XLOOKUP(A8,System_B!A:A,System_B!D:D) -> 71 | F8: Mismatch
A9: TXN1008 | B9: Derivative | C9: Merger | D9: 462 | E9: =_xlfn.XLOOKUP(A9,System_B!A:A,System_B!D:D) -> 462 | F9: Match
A10: TXN1009 | B10: Equity | C10: Split | D10: 211 | E10: =_xlfn.XLOOKUP(A10,System_B!A:A,System_B!D:D) -> 211 | F10: Match
A11: TXN1010 | B11: Derivative | C11: Merger | D11: 255 | E11: =_xlfn.XLOOKUP(A11,System_B!A:A,System_B!D:D) -> 250 | F11: Mismatch
A12: TXN1011 | B12: Mutual Fund | C12: Buyback | D12: 187 | E12: =_xlfn.XLOOKUP(A12,System_B!A:A,System_B!D:D) -> 182 | F12: Mismatch
A13: TXN1012 | B13: Equity | C13: Merger | D13: 83 | E13: =_xlfn.XLOOKUP(A13,System_B!A:A,System_B!D:D) -> 83 | F13: Match
... A51: TXN1050 | B51: Derivative | C51: Merger | D51: 455 | E51: =_xlfn.XLOOKUP(A51,System_B!A:A,System_B!D:D) -> 460 | F51: Mismatch

Sheet System_A
A1: Transaction_ID | B1: Security_Type | C1: ISIN | D1: Quantity | E1: Trade_Value | F1: Corporate_Action_Type | G1: Date | H1: Status
A2: TXN1001 | B2: Equity | C2: IN00407419 | D2: 481 | E2: 37219.25 | F2: Buyback | G2: 45502 | H2: Completed
A3: TXN1002 | B3: Equity | C3: IN00969693 | D3: 443 | E3: 33856.36 | F3: Buyback | G3: 45531 | H3: Completed
A4: TXN1003 | B4: ETF | C4: IN00759176 | D4: 447 | E4: 25390.69 | F4: Merger | G4: 45319 | H4: Completed
A5: TXN1004 | B5: Bond | C5: IN00748564 | D5: 78 | E5: 33835.54 | F5: Bonus Issue | G5: 45636 | H5: Completed
A6: TXN1005 | B6: Bond | C6: IN00479201 | D6: 167 | E6: 28722 | F6: Buyback | G6: 45626 | H6: Completed
A7: TXN1006 | B7: Bond | C7: IN00705397 | D7: 470 | E7: 20056.56 | F7: Bonus Issue | G7: 45622 | H7: Completed
A8: TXN1007 | B8: Equity | C8: IN00301629 | D8: 66 | E8: 32129.04 | F8: Split | G8: 45342 | H8: Completed
A9: TXN1008 | B9: Derivative | C9: IN00838797 | D9: 462 | E9: 47697.23 | F9: Merger | G9: 45323 | H9: Completed
A10: TXN1009 | B10: Equity | C10: IN00172933 | D10: 211 | E10: 37211.34 | F10: Split | G10: 45498 | H10: Completed
A11: TXN1010 | B11: Derivative | C11: IN00148050 | D11: 255 | E11: 14582.07 | F11: Merger | G11: 45465 | H11: Completed
A12: TXN1011 | B12: Mutual Fund | C12: IN00793384 | D12: 187 | E12: 45391.54 | F12: Buyback | G12: 45347 | H12: Completed
A13: TXN1012 | B13: Equity | C13: IN00338968 | D13: 83 | E13: 40035.11 | F13: Merger | G13: 45419 | H13: Completed
... A51: TXN1050 | B51: Derivative | C51: IN00440035 | D51: 455 | E51: 16605.08 | F51: Merger | G51: 45630 | H51: Completed

Sheet System_B
A1: Transaction_ID | B1: Security_Type | C1: ISIN | D1: Quantity | E1: Trade_Value | F1: Corporate_Action_Type | G1: Date | H1: Status
A2: TXN1001 | B2: Mutual Fund | C2: IN00109767 | D2: 481 | E2: 36719.25 | F2: Buyback | G2: 45627 | H2: Completed
A3: TXN1002 | B3: Bond | C3: IN00580547 | D3: 448 | E3: 33356.36 | F3: Merger | G3: 45456 | H3: Completed
A4: TXN1003 | B4: Bond | C4: IN00751332 | D4: 447 | E4: 24890.69 | F4: Split | G4: 45530 | H4: Completed
A5: TXN1004 | B5: ETF | C5: IN00690341 | D5: 78 | E5: 33335.54 | F5: Split | G5: 45518 | H5: Completed
A6: TXN1005 | B6: Bond | C6: IN00204837 | D6: 162 | E6: 28722 | F6: Merger | G6: 45518 | H6: Completed
A7: TXN1006 | B7: Equity | C7: IN00176819 | D7: 465 | E7: 19556.56 | F7: Buyback | G7: 45637 | H7: Completed
A8: TXN1007 | B8: Derivative | C8: IN00663750 | D8: 71 | E8: 31629.04 | F8: Buyback | G8: 45401 | H8: Completed
A9: TXN1008 | B9: Derivative | C9: IN00323508 | D9: 462 | E9: 48197.23 | F9: Dividend | G9: 45553 | H9: Completed
A10: TXN1009 | B10: Equity | C10: IN00630458 | D10: 211 | E10: 37211.34 | F10: Merger | G10: 45534 | H10: Completed
A11: TXN1010 | B11: ETF | C11: IN00378082 | D11: 250 | E11: 14582.07 | F11: Buyback | G11: 45378 | H11: Completed
A12: TXN1011 | B12: Equity | C12: IN00238890 | D12: 182 | E12: 45891.54 | F12: Bonus Issue | G12: 45629 | H12: Completed
A13: TXN1012 | B13: Equity | C13: IN00465962 | D13: 83 | E13: 40535.11 | F13: Split | G13: 45335 | H13: Completed
... A51: TXN1050 | B51: Equity | C51: IN00994343 | D51: 460 | E51: 16105.08 | F51: Buyback | G51: 45648 | H51: Completed
